greentext2vid/__init__.py
greentext2vid/video_generator.py
greentext_to_video-1.0.1.dist-info/LICENSE
greentext_to_video-1.0.1.dist-info/METADATA
greentext_to_video-1.0.1.dist-info/WHEEL
greentext_to_video-1.0.1.dist-info/top_level.txt
greentext_to_video-1.0.1.dist-info/RECORD
