Metadata-Version: 2.1
Name: greentext-to-video
Version: 1.0.1
Summary: Python library to generate a video from a greentext url in tiktok/shorts style
Author: Christian Fiore
License: GNU GENERAL PUBLIC LICENSE
Project-URL: Homepage, https://github.com/agente3z/greentext-to-video
License-File: LICENSE
Requires-Dist: basc-py4chan
Requires-Dist: pillow
Requires-Dist: gtts
Requires-Dist: moviepy
